ukrr_models/__init__.py
ukrr_models/experimental_models.py
ukrr_models/nhsbt_models.py
ukrr_models/rr_models.py
ukrr_models-3.1.0.dist-info/LICENSE
ukrr_models-3.1.0.dist-info/METADATA
ukrr_models-3.1.0.dist-info/WHEEL
ukrr_models-3.1.0.dist-info/RECORD
