Metadata-Version: 2.3
Name: ukrr-models
Version: 3.1.0
Summary: Models of the UKRR database
License: MIT
Author: UK Renal Registry
Requires-Python: >=3.9,<4.0
Classifier: License :: OSI Approved :: MIT License
Classifier: Programming Language :: Python :: 3
Classifier: Programming Language :: Python :: 3.9
Classifier: Programming Language :: Python :: 3.10
Classifier: Programming Language :: Python :: 3.11
Classifier: Programming Language :: Python :: 3.12
Classifier: Programming Language :: Python :: 3.13
Requires-Dist: sqlalchemy (>=2.0.0,<3.0.0)
